vsifile/__init__.py
vsifile/logger.py
vsifile/py.typed
vsifile/rasterio.py
vsifile/settings.py
vsifile/io/__init__.py
vsifile/io/base.py
vsifile/io/file.py
vsifile/io/http.py
vsifile/io/s3.py
vsifile-0.5.0.dist-info/METADATA
vsifile-0.5.0.dist-info/WHEEL
vsifile-0.5.0.dist-info/licenses/LICENSE
vsifile-0.5.0.dist-info/RECORD
