Metadata-Version: 2.4
Name: vsifile
Version: 0.5.0
Summary: Super simple file reader.
Project-URL: Homepage, https://developmentseed.github.io/vsifile/
Project-URL: Documentation, https://vincentsarago.github.io/vsifile/
Project-URL: Issues, https://github.com/vincentsarago/vsifile/issues
Project-URL: Source, https://github.com/vincentsarago/vsifile
Project-URL: Changelog, https://vincentsarago.github.io/vsifile/release-notes/
Author-email: Vincent Sarago <vincent@developmentseed.com>
License: MIT License
License-File: LICENSE
Classifier: Intended Audience :: Information Technology
Classifier: Intended Audience :: Science/Research
Classifier: License :: OSI Approved :: BSD License
Classifier: Programming Language :: Python :: 3.11
Classifier: Programming Language :: Python :: 3.12
Classifier: Programming Language :: Python :: 3.13
Classifier: Topic :: Scientific/Engineering :: GIS
Requires-Python: >=3.11
Requires-Dist: attrs
Requires-Dist: cachetools
Requires-Dist: diskcache
Requires-Dist: httpx
Requires-Dist: obstore<0.9,>=0.5
Requires-Dist: pydantic
Requires-Dist: pydantic-settings
